core/__init__.py
core/knowledge/__init__.py
core/standards/__init__.py
core/standards/spwla.py
labs/__init__.py
labs/auto_compliance/__init__.py
labs/basin_gpts/__init__.py
ops/__init__.py
ops/prompt_factory/__init__.py
ops/training_pipeline/__init__.py
products/__init__.py
products/excel_geotools/__init__.py
products/las_validator_pro/__init__.py
products/las_validator_pro/cli.py
products/litho_assistant/__init__.py
services/__init__.py
services/llm_gateway/__init__.py
services/monetization/__init__.py
geolapis_core-0.1.1.dist-info/METADATA
geolapis_core-0.1.1.dist-info/WHEEL
geolapis_core-0.1.1.dist-info/entry_points.txt
geolapis_core-0.1.1.dist-info/top_level.txt
geolapis_core-0.1.1.dist-info/RECORD
