Metadata-Version: 2.4
Name: geolapis-core
Version: 0.1.1
Summary: Fast LAS file sanity checks for petrophysicists
Home-page: https://www.geolapis.com
Author: NI Ezema / Geolapis Ltd
Author-email: contact@geolapis.com
Project-URL: Documentation, https://www.geolapis.com/docs
Project-URL: Source, https://github.com/GeolapisLtd/GeolapisCore
Project-URL: Issues, https://github.com/GeolapisLtd/GeolapisCore/issues
Classifier: Development Status :: 4 - Beta
Classifier: Intended Audience :: Science/Research
Classifier: License :: OSI Approved :: MIT License
Classifier: Programming Language :: Python :: 3
Classifier: Programming Language :: Python :: 3.7
Classifier: Programming Language :: Python :: 3.8
Classifier: Programming Language :: Python :: 3.9
Classifier: Programming Language :: Python :: 3.10
Classifier: Topic :: Scientific/Engineering :: GIS
Classifier: Operating System :: OS Independent
Requires-Python: >=3.7
Requires-Dist: lasio>=0.27.0
Requires-Dist: rich>=13.0.0
Dynamic: author
Dynamic: author-email
Dynamic: classifier
Dynamic: description
Dynamic: description-content-type
Dynamic: home-page
Dynamic: project-url
Dynamic: requires-dist
Dynamic: requires-python
Dynamic: summary
